yggdrasil/__init__.py
yggdrasil/endpoints/__init__.py
yggdrasil/endpoints/handlers.py
yggdrasil/endpoints/profile.py
yggdrasil/endpoints/query.py
yggdrasil/endpoints/root.py
yggdrasil/endpoints/session.py
yggdrasil/endpoints/user.py
yggdrasil/exceptions.py
yggdrasil/handlers/__init__.py
yggdrasil/handlers/proto.py
yggdrasil/handlers/register.py
yggdrasil/models/__init__.py
yggdrasil/models/root.py
yggdrasil/models/session.py
yggdrasil/models/user.py
yggdrasil/utils/__init__.py
yggdrasil/utils/context.py
yggdrasil/utils/upstream.py
yggdrasil_scaffold-0.1.0.dev6.dist-info/LICENSE
yggdrasil_scaffold-0.1.0.dev6.dist-info/METADATA
yggdrasil_scaffold-0.1.0.dev6.dist-info/WHEEL
yggdrasil_scaffold-0.1.0.dev6.dist-info/RECORD
