Metadata-Version: 2.1
Name: yggdrasil-scaffold
Version: 0.1.0.dev6
Summary: Yggdrasil Scaffold for Authlib-injector
Home-page: https://github.com/Silverteal/yggdrasil-scaffold
License: MIT
Keywords: minecraft,mc,authlib,authlib-injector,implementaion,api,yggdrasil
Author: Silverteal
Author-email: 67404722+Silverteal@users.noreply.github.com
Requires-Python: >=3.12,<4.0
Classifier: License :: OSI Approved :: MIT License
Classifier: Programming Language :: Python :: 3
Classifier: Programming Language :: Python :: 3.12
Provides-Extra: upstream
Requires-Dist: adofai (>=0.1.0-dev6,<0.2.0)
Requires-Dist: fastapi (>=0.115.0,<0.116.0)
Requires-Dist: pydantic (>=2.9.2,<3.0.0)
Requires-Dist: python-multipart (>=0.0.12,<0.0.13)
Requires-Dist: yggdrasil-client (>=0.1.0.dev8,<0.2.0) ; extra == "upstream"
Project-URL: Repository, https://github.com/Silverteal/yggdrasil-scaffold
